html_to_mp3/__init__.py
html_to_mp3/html_to_mp3.py
html_to_mp3/npr_util.py
html_to_mp3-0.2.0.dist-info/entry_points.txt
html_to_mp3-0.2.0.dist-info/WHEEL
html_to_mp3-0.2.0.dist-info/METADATA
html_to_mp3-0.2.0.dist-info/RECORD
