Metadata-Version: 2.1
Name: html-to-mp3
Version: 0.2.0
Summary: Convert HTML and text to mp3s
Home-page: https://github.com/michaelwooley/html-to-mp3
License: MIT
Author: Michael Wooley
Author-email: wm.wooley@gmail.com
Requires-Python: >=3.9,<4.0
Classifier: License :: OSI Approved :: MIT License
Classifier: Programming Language :: Python :: 3
Classifier: Programming Language :: Python :: 3.9
Requires-Dist: beautifulsoup4 (>=4.9.3,<5.0.0)
Requires-Dist: click (>=7.1.2,<8.0.0)
Requires-Dist: requests (>=2.25.1,<3.0.0)
Project-URL: Repository, https://github.com/michaelwooley/html-to-mp3
